Workbook

Sheet SUM OF SALES
A3: Row Labels | B3: Sum of Sales | C3: Sum of Profit
A4: Canada | B4: 24887655 | C4: 3529228.9
A5: France | B5: 24354172 | C5: 3781020.8
A6: Germany | B6: 23505341 | C6: 3680388.8
A7: Mexico | B7: 20949352 | C7: 2907523.1
A8: United States of America | B8: 25029830 | C8: 2995540.7
A9: Grand Total | B9: 1.1872635e+08 | C9: 16893702

Sheet Sheet3
A1: t-Test: Two-Sample Assuming Unequal Variances
B3: 1618.5 | C3: 3
A4: Mean | B4: 1608.2797 | C4: 96.610873
A5: Variance | B5: 753508.92 | C5: 11798.888
A6: Observations | B6: 699 | C6: 699
A7: Hypothesized Mean Difference | B7: 0
A8: df | B8: 720
A9: t Stat | B9: 45.685372
A10: P(T<=t) one-tail | B10: 3.1632745e-215
A11: t Critical one-tail | B11: 1.6469727
A12: P(T<=t) two-tail | B12: 6.326549e-215
A13: t Critical two-tail | B13: 1.9632643

Sheet Sheet4
A1: t-Test: Two-Sample Assuming Unequal Variances
B3: 32370 | C3: 0
A4: Mean | B4: 169805.41 | C4: 13169.168
A5: Variance | B5: 5.6092627e+10 | C5: 5.2780343e+08
A6: Observations | B6: 699 | C6: 699
A7: Hypothesized Mean Difference | B7: 0
A8: df | B8: 711
A9: t Stat | B9: 17.403807
A10: P(T<=t) one-tail | B10: 4.4185082e-57
A11: t Critical one-tail | B11: 1.6469996
A12: P(T<=t) two-tail | B12: 8.8370165e-57
A13: t Critical two-tail | B13: 1.9633061

Sheet T TEST
A1: t-Test: Two-Sample Assuming Unequal Variances | G1: t-Test: Two-Sample Assuming Unequal Variances
B3: Units Sold | C3: Manufacturing Price | H3: Sales | I3: Discounts
A4: Mean | B4: 1608.2943 | C4: 96.477143 | G4: Mean | H4: 169609.07 | I4: 13150.355
A5: Variance | B5: 752431.09 | C5: 11794.527 | G5: Variance | H5: 5.6039363e+10 | I5: 5.272961e+08
A6: Observations | B6: 700 | C6: 700 | G6: Observations | H6: 700 | I6: 700
A7: Hypothesized Mean Difference | B7: 0 | G7: Hypothesized Mean Difference | H7: 0
A8: df | B8: 721 | G8: df | H8: 712
A9: t Stat | B9: 45.754887 | G9: t Stat | H9: 17.404779
A10: P(T<=t) one-tail | B10: 1.0275909e-215 | G10: P(T<=t) one-tail | H10: 4.244587e-57
A11: t Critical one-tail | B11: 1.6469698 | G11: t Critical one-tail | H11: 1.6469966
A12: P(T<=t) two-tail | B12: 2.0551817e-215 | G12: P(T<=t) two-tail | H12: 8.489174e-57
A13: t Critical two-tail | B13: 1.9632597 | G13: t Critical two-tail | H13: 1.9633014

Sheet Sheet7
A1: t-Test: Two-Sample Assuming Unequal Variances
B3: Sales | C3: Discounts
A4: Mean | B4: 338649.36 | C4: 26344.012
A5: Variance | B5: 1.9965559e+13 | C5: 1.2022605e+11
A6: Observations | B6: 706 | C6: 706
A7: Hypothesized Mean Difference | B7: 0
A8: df | B8: 713
A9: t Stat | B9: 1.8515582
A10: P(T<=t) one-tail | B10: 0.03225128
A11: t Critical one-tail | B11: 1.6469935
A12: P(T<=t) two-tail | B12: 0.064502559
A13: t Critical two-tail | B13: 1.9632967

Sheet Sheet8
A1: t-Test: Two-Sample Assuming Unequal Variances
B3: Sales | C3: Discounts
A4: Mean | B4: 169609.07 | C4: 13150.355
A5: Variance | B5: 5.6039363e+10 | C5: 5.272961e+08
A6: Observations | B6: 700 | C6: 700
A7: Hypothesized Mean Difference | B7: 0
A8: df | B8: 712
A9: t Stat | B9: 17.404779
A10: P(T<=t) one-tail | B10: 4.244587e-57
A11: t Critical one-tail | B11: 1.6469966
A12: P(T<=t) two-tail | B12: 8.489174e-57
A13: t Critical two-tail | B13: 1.9633014

Sheet Segments percentage
A3: Sum of Sales | B3: Column Labels
A4: Row Labels | B4: Canada | C4: France | D4: Germany | E4: Mexico | F4: United States of America | G4: Grand Total
A5: Channel Partners | B5: 0.019735252 | C5: 0.0152783 | D5: 0.014312742 | E5: 0.011187892 | F5: 0.014643894 | G5: 0.015165914
A6: Enterprise | B6: 0.15941603 | C6: 0.15976279 | D6: 0.17386799 | E6: 0.15828085 | F6: 0.1738168 | G6: 0.16518401
A7: Government | B7: 0.43158894 | C7: 0.49797557 | D7: 0.48724654 | E7: 0.4673939 | F7: 0.33522985 | G7: 0.44222921
A8: Midmarket | B8: 0.020500685 | C8: 0.024381944 | D8: 0.012820267 | E8: 0.024398673 | F8: 0.018593249 | G8: 0.020061958
A9: Small Business | B9: 0.36875909 | C9: 0.30260139 | D9: 0.31175247 | E9: 0.33873869 | F9: 0.45771621 | G9: 0.3573589
A10: Grand Total | B10: 1 | C10: 1 | D10: 1 | E10: 1 | F10: 1 | G10: 1

Sheet segments
A3: Row Labels | B3: Sum of Sale Price | C3: Sum of Sales | D3: Sum of COGS | E3: Sum of Profit
A4: Channel Partners | B4: 1200 | C4: 1800593.6 | D4: 483790.5 | E4: 1316803.1
A5: Enterprise | B5: 12500 | C5: 19611694 | D5: 20226240 | E5: -614545.62
A6: Government | B6: 37700 | C6: 52504261 | D6: 41116088 | E6: 11388173
A7: Midmarket | B7: 1500 | C7: 2381883.1 | D7: 1721780 | E7: 660103.07
A8: Small Business | B8: 30000 | C8: 42427918 | D8: 38284750 | E8: 4143168.5
A9: Grand Total | B9: 82900 | C9: 1.1872635e+08 | D9: 101832648 | E9: 16893702

Sheet country wise discount band
A3: Sum of Units Sold | B3: Column Labels
A4: Row Labels | B4: High | C4: Low | D4: Medium | E4: None
A5: Canada | B5: 94861 | C5: 61140.5 | D5: 71613 | E5: 19814
A6: France | B6: 80157.5 | C6: 55735.5 | D6: 88103 | E6: 16935
A7: Germany | B7: 52010 | C7: 52174.5 | D7: 71746 | E7: 25563.5
A8: Mexico | B8: 78860 | C8: 40731 | D8: 71226 | E8: 12508
A9: United States of America | B9: 92197 | C9: 52077 | D9: 77010.5 | E9: 11343

Sheet year wise profit and unit sold
A3: Row Labels | B3: Sum of Profit | C3: Sum of Units Sold
A4: Canada | B4: 3529228.9 | C4: 247428.5
A5: 2013 | B5: 803671.78 | C5: 62291
A6: 2014 | B6: 2725557.1 | C6: 185137.5
A7: France | B7: 3781020.8 | C7: 240931
A8: 2013 | B8: 811332.17 | C8: 51326
A9: 2014 | B9: 2969688.6 | C9: 189605
A10: Germany | B10: 3680388.8 | C10: 201494
A11: 2013 | B11: 1118219.5 | C11: 54272
A12: 2014 | B12: 2562169.4 | C12: 147222
A13: Mexico | B13: 2907523.1 | C13: 203325
A14: 2013 | B14: 592670.26 | C14: 49305
A15: 2014 | B15: 2314852.8 | C15: 154020
... A19: Grand Total | B19: 16893702 | C19: 1125806

Sheet Sheet17
A3: Row Labels | B3: Sum of Sales | C3: Sum of Discounts | D3: Sum of COGS
A4: Canada | B4: 24887655 | C4: 2044508.6 | D4: 21358426
A5: 2013 | B5: 5175888.8 | C5: 379497.22 | D5: 4372217
A6: 2014 | B6: 19711766 | C6: 1665011.4 | D6: 16986209
A7: France | B7: 24354172 | C7: 1727502.2 | D7: 20573152
A8: 2013 | B8: 5132795.2 | C8: 448087.83 | D8: 4321463
A9: 2014 | B9: 19221377 | C9: 1279414.4 | D9: 16251688
A10: Germany | B10: 23505341 | C10: 1416126.7 | D10: 19824952
A11: 2013 | B11: 6227735.5 | C11: 402529.53 | D11: 5109516
A12: 2014 | B12: 17277605 | C12: 1013597.2 | D12: 14715436
A13: Mexico | B13: 20949352 | C13: 1777582.9 | D13: 18041829
A14: 2013 | B14: 4754421.3 | C14: 396479.74 | D14: 4161751
A15: 2014 | B15: 16194931 | C15: 1381103.2 | D15: 13880078
... A19: Grand Total | B19: 1.1872635e+08 | C19: 9205248.2 | D19: 101832648

Sheet Sheet5

Sheet sum of profit by segment and ye
B3: Column Labels
B4: 2013 | D4: 2014 | F4: Total Sum of Sales | G4: Total Sum of Profit
A5: Row Labels | B5: Sum of Sales | C5: Sum of Profit | D5: Sum of Sales | E5: Sum of Profit
A6: Channel Partners | B6: 398090.28 | C6: 289889.28 | D6: 1402503.4 | E6: 1026913.9 | F6: 1800593.6 | G6: 1316803.1
A7: Enterprise | B7: 4049562.5 | C7: -193757.5 | D7: 15562132 | E7: -420788.12 | F7: 19611694 | G7: -614545.62
A8: Government | B8: 13085685 | C8: 2886645.3 | D8: 39418575 | E8: 8501527.9 | F8: 52504261 | G8: 11388173
A9: Midmarket | B9: 546243.45 | C9: 151763.45 | D9: 1835639.6 | E9: 508339.62 | F9: 2381883.1 | G9: 660103.07
A10: Small Business | B10: 8335674 | C10: 743924 | D10: 34092244 | E10: 3399244.5 | F10: 42427918 | G10: 4143168.5
A11: Grand Total | B11: 26415256 | C11: 3878464.5 | D11: 92311095 | E11: 13015238 | F11: 1.1872635e+08 | G11: 16893702

Sheet Sheet9
A3: Row Labels | B3: Min of COGS | C3: Count of Year | D3: Min of Sales | E3: Average of Discounts | F3: Average of Profit | G3: Min of Sale Price
A4: Canada | B4: 1285 | C4: 140 | D4: 1655.08 | E4: 14603.633 | F4: 25208.778 | G4: 7
A5: France | B5: 918 | C5: 140 | D5: 1763.86 | E5: 12339.302 | F5: 27007.291 | G5: 7
A6: Germany | B6: 1101 | C6: 140 | D6: 1685.6 | E6: 10115.191 | F6: 26288.492 | G6: 7
A7: Mexico | B7: 1101 | C7: 140 | D7: 2508.66 | E7: 12697.021 | F7: 20768.022 | G7: 7
A8: United States of America | B8: 1158 | C8: 140 | D8: 1730.54 | E8: 15996.627 | F8: 21396.719 | G8: 7
A9: Grand Total | B9: 918 | C9: 700 | D9: 1655.08 | E9: 13150.355 | F9: 24133.86 | G9: 7

Sheet Sheet2
A1: DASHBOARD

Sheet Sheet11
A3: Row Labels | B3: Sum of Sale Price | C3: Sum of Sales | D3: Sum of COGS | E3: Sum of Profit
A4: Channel Partners | B4: 1200 | C4: 1800593.6 | D4: 483790.5 | E4: 1316803.1
A5: Enterprise | B5: 12500 | C5: 19611694 | D5: 20226240 | E5: -614545.62
A6: Government | B6: 37700 | C6: 52504261 | D6: 41116088 | E6: 11388173
A7: Midmarket | B7: 1500 | C7: 2381883.1 | D7: 1721780 | E7: 660103.07
A8: Small Business | B8: 30000 | C8: 42427918 | D8: 38284750 | E8: 4143168.5
A9: Grand Total | B9: 82900 | C9: 1.1872635e+08 | D9: 101832648 | E9: 16893702

Sheet segment wise discount
A1: Country | B1: (All)
A3: Sum of Discounts | B3: Column Labels
A4: Row Labels | B4: High | C4: Low | D4: Medium | E4: None | F4: Grand Total
A5: Channel Partners | B5: 81346.62 | C5: 9520.5 | D5: 43701.24 | E5: 0 | F5: 134568.36
A6: Enterprise | B6: 920341.25 | C6: 162409.38 | D6: 374555 | E6: 0 | F6: 1457305.6
A7: Government | B7: 2314897.3 | C7: 423711.92 | D7: 1160196.6 | E7: 0 | F7: 3898805.8
A8: Midmarket | B8: 135818.1 | C8: 11827.5 | D8: 53141.325 | E8: 0 | F8: 200786.92
A9: Small Business | B9: 1864623 | C9: 278206.5 | D9: 1370952 | E9: 0 | F9: 3513781.5
A10: Grand Total | B10: 5317026.3 | C10: 885675.8 | D10: 3002546.2 | E10: 0 | F10: 9205248.2
G19: The graph inficates prefer government to high discount band allocatation

Sheet Sheet6
A3: Sum of Profit | B3: Column Labels
A4: Row Labels | B4: 2013 | C4: 2014 | D4: Grand Total
A5: Amarilla | B5: 781949.53 | C5: 2032154.5 | D5: 2814104.1
A6: Carretera | B6: 38768.86 | C6: 1788036 | D6: 1826804.9
A7: Montana | B7: 457758.04 | C7: 1656996.8 | D7: 2114754.9
A8: Paseo | B8: 1099853.1 | C8: 3697584.9 | D8: 4797438
A9: Velo | B9: 621949.76 | C9: 1684042.7 | D9: 2305992.5
A10: VTT | B10: 878185.23 | C10: 2156422.8 | D10: 3034608
A11: Grand Total | B11: 3878464.5 | C11: 13015238 | D11: 16893702

Sheet Sheet1
A1: Segment | B1: Country | C1: Product | D1: Discount Band | E1: Units Sold | F1: Manufacturing Price | G1: Sale Price | H1: Gross Sales | I1: Discounts | J1: Sales | K1: COGS | L1: Profit | M1: Date | N1: Month Number | O1: Month Name | P1: Year
A2: Government | B2: Canada | C2: Carretera | D2: None | E2: 1618.5 | F2: 3 | G2: 20 | H2: 32370 | I2: 0 | J2: 32370 | K2: 16185 | L2: 16185 | M2: 41640 | N2: 1 | O2: January | P2: 2014
A3: Government | B3: Germany | C3: Carretera | D3: None | E3: 1321 | F3: 3 | G3: 20 | H3: 26420 | I3: 0 | J3: 26420 | K3: 13210 | L3: 13210 | M3: 41640 | N3: 1 | O3: January | P3: 2014
A4: Midmarket | B4: France | C4: Carretera | D4: None | E4: 2178 | F4: 3 | G4: 15 | H4: 32670 | I4: 0 | J4: 32670 | K4: 21780 | L4: 10890 | M4: 41791 | N4: 6 | O4: June | P4: 2014
A5: Midmarket | B5: Germany | C5: Carretera | D5: None | E5: 888 | F5: 3 | G5: 15 | H5: 13320 | I5: 0 | J5: 13320 | K5: 8880 | L5: 4440 | M5: 41791 | N5: 6 | O5: June | P5: 2014
A6: Midmarket | B6: Mexico | C6: Carretera | D6: None | E6: 2470 | F6: 3 | G6: 15 | H6: 37050 | I6: 0 | J6: 37050 | K6: 24700 | L6: 12350 | M6: 41791 | N6: 6 | O6: June | P6: 2014
A7: Government | B7: Germany | C7: Carretera | D7: None | E7: 1513 | F7: 3 | G7: 350 | H7: 529550 | I7: 0 | J7: 529550 | K7: 393380 | L7: 136170 | M7: 41974 | N7: 12 | O7: December | P7: 2014
A8: Midmarket | B8: Germany | C8: Montana | D8: None | E8: 921 | F8: 5 | G8: 15 | H8: 13815 | I8: 0 | J8: 13815 | K8: 9210 | L8: 4605 | M8: 41699 | N8: 3 | O8: March | P8: 2014
A9: Channel Partners | B9: Canada | C9: Montana | D9: None | E9: 2518 | F9: 5 | G9: 12 | H9: 30216 | I9: 0 | J9: 30216 | K9: 7554 | L9: 22662 | M9: 41791 | N9: 6 | O9: June | P9: 2014
A10: Government | B10: France | C10: Montana | D10: None | E10: 1899 | F10: 5 | G10: 20 | H10: 37980 | I10: 0 | J10: 37980 | K10: 18990 | L10: 18990 | M10: 41791 | N10: 6 | O10: June | P10: 2014
A11: Channel Partners | B11: Germany | C11: Montana | D11: None | E11: 1545 | F11: 5 | G11: 12 | H11: 18540 | I11: 0 | J11: 18540 | K11: 4635 | L11: 13905 | M11: 41791 | N11: 6 | O11: June | P11: 2014
A12: Midmarket | B12: Mexico | C12: Montana | D12: None | E12: 2470 | F12: 5 | G12: 15 | H12: 37050 | I12: 0 | J12: 37050 | K12: 24700 | L12: 12350 | M12: 41791 | N12: 6 | O12: June | P12: 2014
A13: Enterprise | B13: Canada | C13: Montana | D13: None | E13: 2665.5 | F13: 5 | G13: 125 | H13: 333187.5 | I13: 0 | J13: 333187.5 | K13: 319860 | L13: 13327.5 | M13: 41821 | N13: 7 | O13: July | P13: 2014
... A701: Channel Partners | B701: United States of America | C701: VTT | D701: High | E701: 1806 | F701: 250 | G701: 12 | H701: 21672 | I701: 3250.8 | J701: 18421.2 | K701: 5418 | L701: 13003.2 | M701: 41760 | N701: 5 | O701: May | P701: 2014
E703: ANALYZE THE DATASET
D704: TOTAL | E704: =SUM(E2:E701) -> 1125806 | F704: =SUM(F2:F701) -> 67534 | G704: =SUM(G2:G701) -> 82900 | H704: =SUM(H2:H701) -> 1.279316e+08 | I704: =SUM(I2:I701) -> 9205248.2 | J704: =SUM(J2:J701) -> 1.1872635e+08 | K704: =SUM(K2:K701) -> 101832648 | L704: =SUM(L2:L701) -> 16893702
D705: AVERAGE | E705: =AVERAGE(E2:E701) -> 1608.2943 | F705: =AVERAGE(F2:F701) -> 96.477143 | G705: =AVERAGE(G2:G701) -> 118.42857 | H705: =AVERAGE(H2:H701) -> 182759.43 | I705: =AVERAGE(I2:I701) -> 13150.355 | J705: =AVERAGE(J2:J701) -> 169609.07 | K705: =AVERAGE(K2:K701) -> 145475.21 | L705: =AVERAGE(L2:L701) -> 24133.86
D706: MEDIAN | E706: =MEDIAN(E2:E701) -> 1542.5 | F706: =MEDIAN(F2:F701) -> 10 | G706: =MEDIAN(G2:G701) -> 20 | H706: =MEDIAN(H2:H701) -> 37980 | I706: =MEDIAN(I2:I701) -> 2585.25 | J706: =MEDIAN(J2:J701) -> 35540.2 | K706: =MEDIAN(K2:K701) -> 22506.25 | L706: =MEDIAN(L2:L701) -> 9242.2
D707: MODE | E707: =MODE(E2:E701) -> 727 | F707: =MODE(F2:F701) -> 10 | G707: =MODE(G2:G701) -> 20 | H707: =MODE(H2:H701) -> 37050 | I707: =MODE(I2:I701) -> 0 | J707: =MODE(J2:J701) -> 32670 | K707: =MODE(K2:K701) -> 17430 | L707: =MODE(L2:L701) -> 0
D708: STDDEVA | E708: =STDEV(E2:E701) -> 867.42786 | F708: =STDEV(F2:F701) -> 108.60261 | G708: =STDEV(G2:G701) -> 136.77551 | H708: =STDEV(H2:H701) -> 254262.28 | I708: =STDEV(I2:I701) -> 22962.929 | J708: =STDEV(J2:J701) -> 236726.35 | K708: =STDEV(K2:K701) -> 203865.51 | L708: =STDEV(L2:L701) -> 42760.627
D709: MAX | E709: =MAX(E2:E701) -> 4492.5 | F709: =MAX(F2:F701) -> 260 | G709: =MAX(G2:G701) -> 350 | H709: =MAX(H2:H701) -> 1207500 | I709: =MAX(I2:I701) -> 149677.5 | J709: =MAX(J2:J701) -> 1159200 | K709: =MAX(K2:K701) -> 950625 | L709: =MAX(L2:L701) -> 262200

Sheet Sheet15
A1: Product | B1: Units Sold | C1: Sale Price | D1: Gross Sales | E1: Discounts
A2: Amarilla | B2: 2750 | C2: 350 | D2: 962500 | E2: 0
A3: Amarilla | B3: 1953 | C3: 12 | D3: 23436 | E3: 0
A4: Amarilla | B4: 4219.5 | C4: 125 | D4: 527437.5 | E4: 0
A5: Amarilla | B5: 1899 | C5: 20 | D5: 37980 | E5: 0
A6: Amarilla | B6: 1686 | C6: 7 | D6: 11802 | E6: 0
A7: Amarilla | B7: 2141 | C7: 12 | D7: 25692 | E7: 0 | I7: MEDIAN
A8: Amarilla | B8: 1143 | C8: 7 | D8: 8001 | E8: 0 | G8: Product | H8: Units Sold | I8: Sale Price | J8: Gross Sales | K8: Discounts
A9: Amarilla | B9: 615 | C9: 15 | D9: 9225 | E9: 0 | G9: Carretera | H9: 1513 | I9: 20 | J9: 37050 | K9: 2093.25
A10: Amarilla | B10: 1989 | C10: 12 | D10: 23868 | E10: 238.68 | G10: Montana | H10: 1715 | I10: 20 | J10: 34500 | K10: 2506.68
A11: Amarilla | B11: 321 | C11: 15 | D11: 4815 | E11: 48.15 | G11: Paseo | H11: 1596 | I11: 20 | J11: 34704 | K11: 2460.88
A12: Amarilla | B12: 259 | C12: 300 | D12: 77700 | E12: 1554 | G12: VTT | H12: 1527 | I12: 20 | J12: 43125 | K12: 1989.4
A13: Amarilla | B13: 1101 | C13: 300 | D13: 330300 | E13: 6606 | G13: Amarilla | H13: 1652 | I13: 20 | J13: 38100 | K13: 3951.42
A14: Amarilla | B14: 2276 | C14: 125 | D14: 284500 | E14: 5690 | G14: Velo | H14: 1307 | I14: 20 | J14: 43125 | K14: 1989.4
A15: Amarilla | B15: 2966 | C15: 350 | D15: 1038100 | E15: 20762
A16: Amarilla | B16: 1236 | C16: 20 | D16: 24720 | E16: 494.4
A17: Amarilla | B17: 941 | C17: 20 | D17: 18820 | E17: 376.4
A18: Amarilla | B18: 1916 | C18: 300 | D18: 574800 | E18: 11496
A19: Amarilla | B19: 1865 | C19: 350 | D19: 652750 | E19: 26110
A20: Amarilla | B20: 1074 | C20: 125 | D20: 134250 | E20: 5370
A21: Amarilla | B21: 1907 | C21: 350 | D21: 667450 | E21: 26698
A22: Amarilla | B22: 671 | C22: 15 | D22: 10065 | E22: 402.6
A23: Amarilla | B23: 1778 | C23: 350 | D23: 622300 | E23: 24892
A24: Amarilla | B24: 1683 | C24: 7 | D24: 11781 | E24: 589.05
A25: Amarilla | B25: 1123 | C25: 12 | D25: 13476 | E25: 673.8
A26: Amarilla | B26: 1159 | C26: 7 | D26: 8113 | E26: 405.65
... A701: VTT | B701: 1806 | C701: 12 | D701: 21672 | E701: 3250.8

Sheet Statistical Analysis
A1: Statistical Analysis | B1: Units Sold | C1: Manufacturing Price | D1: Sale Price | E1: Gross Sales | F1: Discounts | G1: Sales | H1: COGS | I1: Profit
A2: Count | B2: =COUNT(Sheet1!E2:E701) -> 700 | C2: =COUNT(Sheet1!F2:F701) -> 700 | D2: =COUNT(Sheet1!G2:G701) -> 700 | E2: =COUNT(Sheet1!H2:H701) -> 700 | F2: =COUNT(Sheet1!I2:I701) -> 700 | G2: =COUNT(Sheet1!J2:J701) -> 700 | H2: =COUNT(Sheet1!K2:K701) -> 700 | I2: =COUNT(Sheet1!L2:L701) -> 700
A3: Kurtosis | B3: =KURT(Sheet1!E2:E701) -> -0.315318 | C3: =KURT(Sheet1!F2:F701) -> -1.4289627 | D3: =KURT(Sheet1!G2:G701) -> -1.176789 | E3: =KURT(Sheet1!H2:H701) -> 2.0543006 | F3: =KURT(Sheet1!I2:I701) -> 7.9057124 | G3: =KURT(Sheet1!J2:J701) -> 2.1886331 | H3: =KURT(Sheet1!K2:K701) -> 1.608463 | I3: =KURT(Sheet1!L2:L701) -> 8.6786162
A4: Maximum | B4: =MAX(Sheet1!E2:E701) -> 4492.5 | C4: =MAX(Sheet1!F2:F701) -> 260 | D4: =MAX(Sheet1!G2:G701) -> 350 | E4: =MAX(Sheet1!H2:H701) -> 1207500 | F4: =MAX(Sheet1!I2:I701) -> 149677.5 | G4: =MAX(Sheet1!J2:J701) -> 1159200 | H4: =MAX(Sheet1!K2:K701) -> 950625 | I4: =MAX(Sheet1!L2:L701) -> 262200
A5: Mean | B5: =AVERAGE(Sheet1!E2:E701) -> 1608.2943 | C5: =AVERAGE(Sheet1!F2:F701) -> 96.477143 | D5: =AVERAGE(Sheet1!G2:G701) -> 118.42857 | E5: =AVERAGE(Sheet1!H2:H701) -> 182759.43 | F5: =AVERAGE(Sheet1!I2:I701) -> 13150.355 | G5: =AVERAGE(Sheet1!J2:J701) -> 169609.07 | H5: =AVERAGE(Sheet1!K2:K701) -> 145475.21 | I5: =AVERAGE(Sheet1!L2:L701) -> 24133.86
A6: Median | B6: =MEDIAN(Sheet1!E2:E701) -> 1542.5 | C6: =MEDIAN(Sheet1!F2:F701) -> 10 | D6: =MEDIAN(Sheet1!G2:G701) -> 20 | E6: =MEDIAN(Sheet1!H2:H701) -> 37980 | F6: =MEDIAN(Sheet1!I2:I701) -> 2585.25 | G6: =MEDIAN(Sheet1!J2:J701) -> 35540.2 | H6: =MEDIAN(Sheet1!K2:K701) -> 22506.25 | I6: =MEDIAN(Sheet1!L2:L701) -> 9242.2
A7: Minimum | B7: =MIN(Sheet1!E2:E701) -> 200 | C7: =MIN(Sheet1!F2:F701) -> 3 | D7: =MIN(Sheet1!G2:G701) -> 7 | E7: =MIN(Sheet1!H2:H701) -> 1799 | F7: =MIN(Sheet1!I2:I701) -> 0 | G7: =MIN(Sheet1!J2:J701) -> 1655.08 | H7: =MIN(Sheet1!K2:K701) -> 918 | I7: =MIN(Sheet1!L2:L701) -> -40617.5
A8: Mode | B8: =MODE(Sheet1!E2:E701) -> 727 | C8: =MODE(Sheet1!F2:F701) -> 10 | D8: =MODE(Sheet1!G2:G701) -> 20 | E8: =MODE(Sheet1!H2:H701) -> 37050 | F8: =MODE(Sheet1!I2:I701) -> 0 | G8: =MODE(Sheet1!J2:J701) -> 32670 | H8: =MODE(Sheet1!K2:K701) -> 17430 | I8: =MODE(Sheet1!L2:L701) -> 0
A9: Range | B9: =B4-B7 -> 4292.5 | C9: =C4-C7 -> 257 | D9: =D4-D7 -> 343 | E9: =E4-E7 -> 1205701 | F9: =F4-F7 -> 149677.5 | G9: =G4-G7 -> 1157544.9 | H9: =H4-H7 -> 949707 | I9: =I4-I7 -> 302817.5
A10: Sample Variance | B10: =_xlfn.VAR.S(Sheet1!E2:E701) -> 752431.09 | C10: =_xlfn.VAR.S(Sheet1!F2:F701) -> 11794.527 | D10: =_xlfn.VAR.S(Sheet1!G2:G701) -> 18707.541 | E10: =_xlfn.VAR.S(Sheet1!H2:H701) -> 6.4649309e+10 | F10: =_xlfn.VAR.S(Sheet1!I2:I701) -> 5.272961e+08 | G10: =_xlfn.VAR.S(Sheet1!J2:J701) -> 5.6039363e+10 | H10: =_xlfn.VAR.S(Sheet1!K2:K701) -> 4.1561145e+10 | I10: =_xlfn.VAR.S(Sheet1!L2:L701) -> 1.8284712e+09
A11: Skewness | B11: =SKEW(Sheet1!E2:E701) -> 0.43615356 | C11: =SKEW(Sheet1!F2:F701) -> 0.59258395 | D11: =SKEW(Sheet1!G2:G701) -> 0.77128187 | E11: =SKEW(Sheet1!H2:H701) -> 1.6739217 | F11: =SKEW(Sheet1!I2:I701) -> 2.6850389 | G11: =SKEW(Sheet1!J2:J701) -> 1.6962952 | H11: =SKEW(Sheet1!K2:K701) -> 1.5490476 | I11: =SKEW(Sheet1!L2:L701) -> 2.7121513
A12: Standard deviation | B12: =_xlfn.STDEV.S(Sheet1!E2:E701) -> 867.42786 | C12: =_xlfn.STDEV.S(Sheet1!F2:F701) -> 108.60261 | D12: =_xlfn.STDEV.S(Sheet1!G2:G701) -> 136.77551 | E12: =_xlfn.STDEV.S(Sheet1!H2:H701) -> 254262.28 | F12: =_xlfn.STDEV.S(Sheet1!I2:I701) -> 22962.929 | G12: =_xlfn.STDEV.S(Sheet1!J2:J701) -> 236726.35 | H12: =_xlfn.STDEV.S(Sheet1!K2:K701) -> 203865.51 | I12: =_xlfn.STDEV.S(Sheet1!L2:L701) -> 42760.627
A13: Standard Error | B13: =_xlfn.STDEV.S(Sheet1!E2:E701)/SQRT(COUNT(Sheet1!E2:E701)) -> 32.785691 | C13: =_xlfn.STDEV.S(Sheet1!F2:F701)/SQRT(COUNT(Sheet1!F2:F701)) -> 4.1047929 | D13: =_xlfn.STDEV.S(Sheet1!G2:G701)/SQRT(COUNT(Sheet1!G2:G701)) -> 5.1696285 | E13: =_xlfn.STDEV.S(Sheet1!H2:H701)/SQRT(COUNT(Sheet1!H2:H701)) -> 9610.211 | F13: =_xlfn.STDEV.S(Sheet1!I2:I701)/SQRT(COUNT(Sheet1!I2:I701)) -> 867.91713 | G13: =_xlfn.STDEV.S(Sheet1!J2:J701)/SQRT(COUNT(Sheet1!J2:J701)) -> 8947.4149 | H13: =_xlfn.STDEV.S(Sheet1!K2:K701)/SQRT(COUNT(Sheet1!K2:K701)) -> 7705.3919 | I13: =_xlfn.STDEV.S(Sheet1!L2:L701)/SQRT(COUNT(Sheet1!L2:L701)) -> 1616.1998
A14: Sum | B14: =SUM(Sheet1!E2:E701) -> 1125806 | C14: =SUM(Sheet1!F2:F701) -> 67534 | D14: =SUM(Sheet1!G2:G701) -> 82900 | E14: =SUM(Sheet1!H2:H701) -> 1.279316e+08 | F14: =SUM(Sheet1!I2:I701) -> 9205248.2 | G14: =SUM(Sheet1!J2:J701) -> 1.1872635e+08 | H14: =SUM(Sheet1!K2:K701) -> 101832648 | I14: =SUM(Sheet1!L2:L701) -> 16893702

Sheet Sheet10
A1: Statistical Analysis | B1: Units Sold | C1: Manufacturing Price | D1: Sale Price | E1: Gross Sales | F1: Discounts | G1: Sales | H1: COGS
B2: 1618.5 | C2: 3 | D2: 20 | E2: 32370 | F2: 0 | G2: 32370 | H2: 16185
B3: 1321 | C3: 3 | D3: 20 | E3: 26420 | F3: 0 | G3: 26420 | H3: 13210
B4: 2178 | C4: 3 | D4: 15 | E4: 32670 | F4: 0 | G4: 32670 | H4: 21780
B5: 888 | C5: 3 | D5: 15 | E5: 13320 | F5: 0 | G5: 13320 | H5: 8880
B6: 2470 | C6: 3 | D6: 15 | E6: 37050 | F6: 0 | G6: 37050 | H6: 24700
B7: 1513 | C7: 3 | D7: 350 | E7: 529550 | F7: 0 | G7: 529550 | H7: 393380
B8: 921 | C8: 5 | D8: 15 | E8: 13815 | F8: 0 | G8: 13815 | H8: 9210
B9: 2518 | C9: 5 | D9: 12 | E9: 30216 | F9: 0 | G9: 30216 | H9: 7554
B10: 1899 | C10: 5 | D10: 20 | E10: 37980 | F10: 0 | G10: 37980 | H10: 18990
B11: 1545 | C11: 5 | D11: 12 | E11: 18540 | F11: 0 | G11: 18540 | H11: 4635
B12: 2470 | C12: 5 | D12: 15 | E12: 37050 | F12: 0 | G12: 37050 | H12: 24700
B13: 2665.5 | C13: 5 | D13: 125 | E13: 333187.5 | F13: 0 | G13: 333187.5 | H13: 319860
... B701: 1806 | C701: 250 | D701: 12 | E701: 21672 | F701: 3250.8 | G701: 18421.2 | H701: 5418
C704: 67534 | D704: 82900 | E704: 1.279316e+08 | F704: 9205248.2 | G704: 1.1872635e+08 | H704: 101832648
C705: 96.477143 | D705: 118.42857 | E705: 182759.43 | F705: 13150.355 | G705: 169609.07 | H705: 145475.21
C706: 10 | D706: 20 | E706: 37980 | F706: 2585.25 | G706: 35540.2 | H706: 22506.25
C707: 10 | D707: 20 | E707: 37050 | F707: 0 | G707: 32670 | H707: 17430
C708: 108.60261 | D708: 136.77551 | E708: 254262.28 | F708: 22962.929 | G708: 236726.35 | H708: 203865.51
C709: 260 | D709: 350 | E709: 1207500 | F709: 149677.5 | G709: 1159200 | H709: 950625
